LICENSE
MANIFEST.in
README.rst
setup.cfg
setup.py
src/pubmed2pdf/__init__.py
src/pubmed2pdf/__main__.py
src/pubmed2pdf/cli.py
src/pubmed2pdf/constants.py
src/pubmed2pdf/utils.py
src/pubmed2pdf.egg-info/PKG-INFO
src/pubmed2pdf.egg-info/SOURCES.txt
src/pubmed2pdf.egg-info/dependency_links.txt
src/pubmed2pdf.egg-info/entry_points.txt
src/pubmed2pdf.egg-info/not-zip-safe
src/pubmed2pdf.egg-info/requires.txt
src/pubmed2pdf.egg-info/top_level.txt