Metadata-Version: 2.1
Name: pubmed2pdf
Version: 0.0.7
Summary: A Python package to download PDFs from OA publications in PubMed
Home-page: https://github.com/ddomingof/PubMed2PDF
Download-URL: https://github.com/ddomingof/PubMed2PDF
Author: Daniel Domingo-Fernández
Author-email: ddomingof@gmail.com
Maintainer: Daniel Domingo-Fernández
Maintainer-email: ddomingof@gmail.com
License: MIT License
Project-URL: Bug Tracker, https://github.com/ddomingof/PubMed2PDF/issues
Project-URL: Source Code, https://github.com/ddomingof/PubMed2PDF
Project-URL: Documentation, https://github.com/ddomingof/PubMed2PDF
Classifier: Development Status :: 4 - Beta
Classifier: Environment :: Console
Classifier: Intended Audience :: Developers
Classifier: Intended Audience :: Science/Research
Classifier: License :: OSI Approved :: Apache Software License
Classifier: Operating System :: OS Independent
Classifier: Programming Language :: Python
Classifier: Programming Language :: Python :: 3.7
Classifier: Programming Language :: Python :: 3.6
Classifier: Programming Language :: Python :: 3 :: Only
Requires-Python: >=3.6
License-File: LICENSE
Requires-Dist: click>=7.0
Requires-Dist: requests>=2.22.0
Requires-Dist: beautifulsoup4>=4.7.1
Requires-Dist: lxml
Requires-Dist: biopython
